{
	"tempo": 82,
	"room" : 70,
    "firstbeat" : 6.08363,
	"range" : 16134,
	"beats": ["G","G","G","G",
		"G","G","G","G",
		"G","G","G","G",
		"G","G","G","G",
		"Em","Em","Em","Em",
		"Em","Em","Em","Em",
		"Am","Am","Am","Am",
		"Am","Am","Am","Am",
		"D","D","D","D",
		"D","D","D","D",
		"G","G","G","G",
		"G","G","G","G",
		"Em","Em","Em","Em",
		"Em","Em","Em","Em",
		"Am","Am","Am","Am",
		"Am","Am","Am","Am",
		"D","D","D","D",
		"D","D","D","D",
		"G","G","G","G",
		"G","G","G","G",
		"Em","Em","Em","Em",
		"Em","Em","Em","Em",
		"Am","Am","Am","Am",
		"Am","Am","Am","Am",
		"D","D","D","D",
		"D","D","D","D",
		"G","G","G","G",
		"G","G","G","G",
		"Em","Em","Em","Em",
		"Em","Em","Em","Em",
		"Am","Am","Am","Am",
		"Am","Am","Am","Am",
		"D","D","D","D",
		"D","D","D","D",
		"G","G","G","G",
		"G","G","G","G",
		"G","G","G","G",
		"G","G","G","G",
		"Em","Em","Em","Em",
		"Em","Em","Em","Em",
		"Am","Am","Am","Am",
		"Am","Am","Am","Am",
		"D","D","D","D",
		"D","D","D","D",
		"G","G","G","G",
		"G","G","G","G",
		"Em","Em","Em","Em",
		"Em","Em","Em","Em",
		"Am","Am","Am","Am",
		"Am","Am","Am","Am",
		"D","D","D","D",
		"D","D","D","D",
		"G","G","G","G",
		"G","G","G","G",
		"Em","Em","Em","Em",
		"Em","Em","Em","Em",
		"Am","Am","Am","Am",
		"Am","Am","Am","Am",
		"D","D","D","D",
		"D","D","D","D",
		"G","G","G","G",
		"G","G","G","G",
		"Em","Em","Em","Em",
		"Em","Em","Em","Em",
		"Am","Am","Am","Am",
		"Am","Am","Am","Am",
		"D","D","D","D",
		"D","D","D","D",
		"G","G","G","G",
		"G","G","G","G"]
}